directsync/__init__.py
directsync/__version__.py
directsync/args_parsing.py
directsync/directsync.py
directsync/file_comparison.py
directsync/serialization.py
directsync-1.2.0.dist-info/LICENSE
directsync-1.2.0.dist-info/METADATA
directsync-1.2.0.dist-info/WHEEL
directsync-1.2.0.dist-info/entry_points.txt
directsync-1.2.0.dist-info/top_level.txt
directsync-1.2.0.dist-info/RECORD
