Metadata-Version: 2.1
Name: directsync
Version: 1.2.0
Summary: Compare(*diff*)/synchronize/backup/mirror folders quickly.
Home-page: https://github.com/Anmol-Singh-Jaggi/directsync.git
Author: Anmol Singh Jaggi
Author-email: anmolj.65@gmail.com
License: MIT
Platform: UNKNOWN
Classifier: Development Status :: 5 - Production/Stable
Classifier: Environment :: Console
Classifier: Intended Audience :: End Users/Desktop
Classifier: Topic :: Desktop Environment
Classifier: Topic :: System :: Archiving :: Backup
Classifier: Topic :: System :: Archiving :: Mirroring
Classifier: License :: OSI Approved :: MIT License
Classifier: Programming Language :: Python :: 3.7
Classifier: Operating System :: OS Independent
Requires-Python: >=3.4.0
Requires-Dist: tqdm
Requires-Dist: binaryornot
Requires-Dist: send2Trash
